timi/__init__.py
timi/main.py
timi-1.0.1.dist-info/METADATA
timi-1.0.1.dist-info/WHEEL
timi-1.0.1.dist-info/entry_points.txt
timi-1.0.1.dist-info/licenses/LICENSE
timi-1.0.1.dist-info/RECORD
