Metadata-Version: 2.4
Name: timi
Version: 1.0.1
Summary: A terminal app to visualize time progress
Author-email: Dandelion75 <Dandelion75@github.com>
License: GPL-3.0-or-later
License-File: LICENSE
Requires-Python: >=3.1
Requires-Dist: rich>=13.0.0
Requires-Dist: textual>=0.36.0
